napari_blossom/__init__.py
napari_blossom/_reader.py
napari_blossom/_sample_data.py
napari_blossom/_widget.py
napari_blossom/_writer.py
napari_blossom/best_model_W_BCE_chpping.h5
napari_blossom/napari.yaml
napari_blossom/path.py
napari_blossom/_tests/__init__.py
napari_blossom/_tests/test_reader.py
napari_blossom/_tests/test_sample_data.py
napari_blossom/_tests/test_widget.py
napari_blossom/_tests/test_writer.py
napari_blossom-0.1.6.dist-info/LICENSE
napari_blossom-0.1.6.dist-info/METADATA
napari_blossom-0.1.6.dist-info/WHEEL
napari_blossom-0.1.6.dist-info/entry_points.txt
napari_blossom-0.1.6.dist-info/top_level.txt
napari_blossom-0.1.6.dist-info/RECORD
