Metadata-Version: 2.1
Name: napari-blossom
Version: 0.1.6
Summary: Segmentation of blossom apple tree images
Home-page: https://github.com/hereariim/napari-blossom
Author: Herearii Metuarea
Author-email: herearii.metuarea@gmail.com
License: BSD-3-Clause
Project-URL: Bug Tracker, https://github.com/hereariim/napari-blossom/issues
Project-URL: Documentation, https://github.com/hereariim/napari-blossom#README.md
Project-URL: Source Code, https://github.com/hereariim/napari-blossom
Project-URL: User Support, https://github.com/hereariim/napari-blossom/issues
Classifier: Development Status :: 2 - Pre-Alpha
Classifier: Framework :: napari
Classifier: Intended Audience :: Developers
Classifier: License :: OSI Approved :: BSD License
Classifier: Operating System :: OS Independent
Classifier: Programming Language :: Python
Classifier: Programming Language :: Python :: 3
Classifier: Programming Language :: Python :: 3 :: Only
Classifier: Programming Language :: Python :: 3.8
Classifier: Programming Language :: Python :: 3.9
Classifier: Programming Language :: Python :: 3.10
Classifier: Topic :: Software Development :: Testing
Requires-Python: >=3.8
License-File: LICENSE
Requires-Dist: numpy >=1.23.0
Requires-Dist: magicgui >=0.6.1
Requires-Dist: qtpy
Requires-Dist: opencv-python-headless >=4.7.0.68
Requires-Dist: tensorflow >=2.11.0
Requires-Dist: scikit-image >=0.19.3
Requires-Dist: napari
Requires-Dist: focal-loss >=0.0.7
Requires-Dist: pillow >=9.3.0
Requires-Dist: tqdm >=4.64.1
Provides-Extra: testing
Requires-Dist: tox ; extra == 'testing'
Requires-Dist: pytest ; extra == 'testing'
Requires-Dist: pytest-cov ; extra == 'testing'
Requires-Dist: pytest-qt ; extra == 'testing'
Requires-Dist: napari ; extra == 'testing'
Requires-Dist: pyqt5 ; extra == 'testing'
